atomid/__init__.py
atomid/annotate.py
atomid/annotate_crystals.py
atomid/crystal/structure_identification.py
atomid/line_defect_analysis/dislocation_extraction.py
atomid/plane_defect_analysis/grain_segmentation.py
atomid/point_defect_analysis/wigner_seitz_method.py
atomid-0.3.11.dist-info/METADATA
atomid-0.3.11.dist-info/WHEEL
atomid-0.3.11.dist-info/RECORD
