Metadata-Version: 2.1
Name: atomID
Version: 0.3.11
Summary: Python package to identify and annotate crystal structure data files
Author: Ninad Bhat
Requires-Python: >=3.9,<4.0.0
Classifier: Programming Language :: Python :: 3
Classifier: Programming Language :: Python :: 3.9
Classifier: Programming Language :: Python :: 3.10
Classifier: Programming Language :: Python :: 3.11
Classifier: Programming Language :: Python :: 3.12
Requires-Dist: annoy (>=1.17.3,<2.0.0)
Requires-Dist: atomrdf (>=0.9.7,<0.10.0)
Requires-Dist: boto3
Requires-Dist: numpy (==1.26.4)
Requires-Dist: rdflib (>=7.0.0,<8.0.0)
Requires-Dist: scikit-learn (>=1.5.1,<2.0.0)
Requires-Dist: urllib3 (<2)
